raw_database/__init__.py
raw_database/base.py
raw_database/action/__init__.py
raw_database/action/insert.py
raw_database/action/queryset.py
raw_database/action/update.py
tests/__init__.py
tests/test.py
raw_database-0.0.4.dist-info/METADATA
raw_database-0.0.4.dist-info/WHEEL
raw_database-0.0.4.dist-info/top_level.txt
raw_database-0.0.4.dist-info/RECORD
