Metadata-Version: 2.1
Name: raw-database
Version: 0.0.4
Summary: Simple Module Using Raw SQL To Get Insert Update Database
Home-page: UNKNOWN
Author: TriNguyen
Author-email: <trinct1412@gmail.com>
License: UNKNOWN
Keywords: python,database,raw database,postgrest,mysql
Platform: UNKNOWN
Classifier: Programming Language :: Python :: 3
Classifier: License :: OSI Approved :: PostgreSQL License
Classifier: Operating System :: MacOS :: MacOS X
Requires-Dist: SQLAlchemy
